{"name": "MgAu", "entry_id": 10777, "calculation_id": 5558, "icsd_id": 58538, "formationenergy_id": 4062315, "duplicate_entry_id": 10777, "composition": "Au1 Mg1", "composition_generic": "AB", "prototype": "CsCl", "spacegroup": "Pm-3m", "volume": 35.3707, "ntypes": 2, "natoms": 2, "unit_cell": [[3.282573, 0.0, 0.0], [0.0, 3.282573, 0.0], [0.0, 0.0, 3.282573]], "sites": ["Au @ 0 0 0", "Mg @ 0.5 0.5 0.5"], "band_gap": 0.0, "delta_e": -0.615378534583335, "stability": 0.001037924999999995, "fit": "standard", "calculation_label": "static"}